sc_qcc_crawler/__init__.py
sc_qcc_crawler/main.py
sc_qcc_crawler/config/__init__.py
sc_qcc_crawler/config/config.py
sc_qcc_crawler/parser/__init__.py
sc_qcc_crawler/parser/detail_parser.py
sc_qcc_crawler/parser/summary_parser.py
sc_qcc_crawler/process/__init__.py
sc_qcc_crawler/process/html_searcher.py
sc_qcc_crawler/tests/__init__.py
sc_qcc_crawler/tests/sample_config/__init__.py
sc_qcc_crawler/tests/sample_config/production.yml
sc_qcc_crawler-0.0.1.dist-info/licenses/LICENSE
sc_qcc_crawler-0.0.1.dist-info/METADATA
sc_qcc_crawler-0.0.1.dist-info/WHEEL
sc_qcc_crawler-0.0.1.dist-info/entry_points.txt
sc_qcc_crawler-0.0.1.dist-info/top_level.txt
sc_qcc_crawler-0.0.1.dist-info/RECORD
