Metadata-Version: 2.4
Name: sc-qcc-crawler
Version: 0.0.1
Summary: python project
Home-page: https://github.com/Scott-Lau/sc-qcc-crawler
Author: Scott Lau
Author-email: exceedego@126.com
License: MIT
Keywords: python
Platform: POSIX
Classifier: Programming Language :: Python :: 3
Classifier: Programming Language :: Python :: 3.9
Classifier: Programming Language :: Python :: 3.10
Classifier: Programming Language :: Python :: 3.11
Classifier: Programming Language :: Python :: 3.12
Classifier: Programming Language :: Python :: 3.13
Classifier: Operating System :: OS Independent
Classifier: Topic :: Software Development
Classifier: Topic :: Utilities
Requires-Python: >=3.9
License-File: LICENSE
Requires-Dist: sc-utilities==0.0.11
Requires-Dist: requests==2.32.3
Requires-Dist: playwright==1.51.0
Requires-Dist: PyYAML==6.0.2
Requires-Dist: setuptools==78.1.0
Requires-Dist: numpy==2.2.5
Requires-Dist: pandas==2.2.3
Requires-Dist: openpyxl==3.1.5
Dynamic: author
Dynamic: author-email
Dynamic: classifier
Dynamic: description
Dynamic: home-page
Dynamic: keywords
Dynamic: license
Dynamic: license-file
Dynamic: platform
Dynamic: requires-dist
Dynamic: requires-python
Dynamic: summary
